carbon_ops/__init__.py
carbon_ops/config.py
carbon_ops/ledger.py
carbon_ops/pipeline.py
co2e-0.0.1.dist-info/METADATA
co2e-0.0.1.dist-info/WHEEL
co2e-0.0.1.dist-info/top_level.txt
co2e-0.0.1.dist-info/RECORD
