Metadata-Version: 2.4
Name: co2e
Version: 0.0.1
Summary: Reserved package name for future Carbon Ops Guardrails distribution.
Author: Scarlet Moore
Requires-Python: >=3.11
Provides-Extra: dev
Requires-Dist: pytest>=8.3; extra == "dev"
Requires-Dist: pytest-cov>=5.0; extra == "dev"
Requires-Dist: ruff>=0.6; extra == "dev"
Requires-Dist: mypy>=1.12; extra == "dev"
Requires-Dist: types-pyyaml; extra == "dev"
Requires-Dist: pytest-asyncio>=0.24; extra == "dev"
Provides-Extra: docs
Requires-Dist: mkdocs-material>=9.5; extra == "docs"
Requires-Dist: mkdocstrings[python]>=0.25; extra == "docs"
